LICENSE.md
MANIFEST.in
README.md
setup.cfg
setup.py
submit.md
ssbjkadmos/__init__.py
ssbjkadmos/config.py
ssbjkadmos.egg-info/PKG-INFO
ssbjkadmos.egg-info/SOURCES.txt
ssbjkadmos.egg-info/dependency_links.txt
ssbjkadmos.egg-info/not-zip-safe
ssbjkadmos.egg-info/requires.txt
ssbjkadmos.egg-info/top_level.txt
ssbjkadmos/tools/SsbjDiscipline.py
ssbjkadmos/tools/__init__.py
ssbjkadmos/tools/aerodynamics/Aerodynamics.py
ssbjkadmos/tools/aerodynamics/__init__.py
ssbjkadmos/tools/dpdxcalc/DpdxCalc.py
ssbjkadmos/tools/dpdxcalc/__init__.py
ssbjkadmos/tools/outputfunctions/Constraints.py
ssbjkadmos/tools/outputfunctions/Objective.py
ssbjkadmos/tools/outputfunctions/__init__.py
ssbjkadmos/tools/performance/Performance.py
ssbjkadmos/tools/performance/__init__.py
ssbjkadmos/tools/propulsion/Propulsion.py
ssbjkadmos/tools/propulsion/__init__.py
ssbjkadmos/tools/structures/Structures.py
ssbjkadmos/tools/structures/__init__.py
ssbjkadmos/utils/__init__.py
ssbjkadmos/utils/database.py
ssbjkadmos/utils/execution.py
ssbjkadmos/utils/general.py
ssbjkadmos/utils/math.py
tests/__init__.py
tests/test_tool_execution.py