Metadata-Version: 1.1
Name: ssbjkadmos
Version: 0.1.10
Summary: Supersonice Business Jet (SSBJ) tools in Python using a central data schema (XML) approach.
Home-page: https://bitbucket.org/imcovangent/ssbjkadmos
Author: Imco van Gent
Author-email: i.vangent@tudelft.nl
License: Apache Software License
Download-URL: https://bitbucket.org/imcovangent/ssbjkadmos/src/master/dist/ssbjkadmos-0.1.10.tar.gzip
Keywords: optimization agile multidisciplinary engineering aircraft design
Platform: UNKNOWN
Classifier: Development Status :: 4 - Beta
Classifier: License :: OSI Approved :: Apache Software License
Classifier: Programming Language :: Python
Classifier: Programming Language :: Python :: 2.7
Classifier: Programming Language :: Python :: 3.7
Classifier: Intended Audience :: Science/Research
Classifier: Topic :: Scientific/Engineering
